m3u8toMP3/__init__.py
m3u8toMP3/__main__.py
m3u8toMP3/converter.py
m3u8toMP3/exceptions.py
m3u8toMP3/file_helper.py
m3u8toMP3/run.py
m3u8toMP3/utils.py
m3u8tomp3-0.1.1.dist-info/METADATA
m3u8tomp3-0.1.1.dist-info/WHEEL
m3u8tomp3-0.1.1.dist-info/RECORD
