Metadata-Version: 2.1
Name: m3u8toMP3
Version: 0.1.1
Summary: Convert your m3u8 files to MP3
Author: Suoslex
Author-email: mtsarev06@gmail.com
Requires-Python: >=3.10,<4.0
Classifier: Programming Language :: Python :: 3
Classifier: Programming Language :: Python :: 3.10
Classifier: Programming Language :: Python :: 3.11
Classifier: Programming Language :: Python :: 3.12
Requires-Dist: httpx (>=0.27.2,<0.28.0)
Requires-Dist: m3u8 (>=6.0.0,<7.0.0)
Requires-Dist: pycryptodome (>=3.20.0,<4.0.0)
Requires-Dist: python-ffmpeg (>=2.0.12,<3.0.0)
